pylhasa/_paths.py
pylhasa/_archive.py
pylhasa/_exceptions.py
pylhasa/_pylhasa.so
pylhasa/__init__.py
pylhasa-0.1.1.dist-info/WHEEL
pylhasa-0.1.1.dist-info/METADATA
pylhasa-0.1.1.dist-info/RECORD
pylhasa-0.1.1.dist-info/licenses/LICENSE
pylhasa-0.1.1.dist-info/licenses/native/vendor/lhasa/COPYING.md
