Metadata-Version: 2.2
Name: pylhasa
Version: 0.1.1
Summary: Cross-platform Python wrapper for liblhasa (LHA/LZH archives)
Author: pylhasa contributors
License: MIT License
Classifier: Programming Language :: Python :: 3
Classifier: Programming Language :: Python :: 3 :: Only
Classifier: Programming Language :: Python :: 3.9
Classifier: Programming Language :: Python :: 3.10
Classifier: Programming Language :: Python :: 3.11
Classifier: Programming Language :: Python :: 3.12
Classifier: Programming Language :: Python :: 3.13
Classifier: Programming Language :: C
Classifier: License :: OSI Approved :: MIT License
Classifier: Operating System :: OS Independent
Project-URL: Homepage, https://github.com/bwhitn/pylhasa
Project-URL: Repository, https://github.com/bwhitn/pylhasa
Project-URL: Issues, https://github.com/bwhitn/pylhasa/issues
Requires-Python: >=3.9
